AUTHORS
MANIFEST.in
README.rst
setup.py
django_ldap_basic_auth/__init__.py
django_ldap_basic_auth/admin.py
django_ldap_basic_auth/backends.py
django_ldap_basic_auth/cache_helper.py
django_ldap_basic_auth/middleware.py
django_ldap_basic_auth/models.py
django_ldap_basic_auth/settings.py
django_ldap_basic_auth/tests.py
django_ldap_basic_auth/views.py
django_ldap_basic_auth.egg-info/PKG-INFO
django_ldap_basic_auth.egg-info/SOURCES.txt
django_ldap_basic_auth.egg-info/dependency_links.txt
django_ldap_basic_auth.egg-info/top_level.txt