Metadata-Version: 1.0
Name: django-ldap-basic-auth
Version: 0.0.3
Summary: Simple middleware that injects the Authorization header in the request after authenticating against a ldap server.
Home-page: https://github.com/gustavosoares/django-ldap-basic-auth
Author: Gustavo Soares Souza
Author-email: gustavosoares@gmail.com
License: BSD
Keywords: revisions versioning history audit
Platform: UNKNOWN
Classifier: Development Status :: 3 - Alpha
Classifier: Environment :: Web Environment
Classifier: Framework :: Django
Classifier: Intended Audience :: Developers
Classifier: License :: OSI Approved :: BSD License
Classifier: Operating System :: OS Independent
Classifier: Programming Language :: Python
Classifier: Topic :: Software Development :: Libraries :: Python Modules
Classifier: Topic :: Utilities
